django_datatable_serverside_mixin/__init__.py
django_datatable_serverside_mixin/datatable.py
django_datatable_serverside_mixin/views.py
tests/__init__.py
tests/fixtures.py
tests/test_datatable.py
tests/test_views.py
django_datatable_serverside_mixin-2.1.1.dist-info/LICENSE
django_datatable_serverside_mixin-2.1.1.dist-info/METADATA
django_datatable_serverside_mixin-2.1.1.dist-info/WHEEL
django_datatable_serverside_mixin-2.1.1.dist-info/top_level.txt
django_datatable_serverside_mixin-2.1.1.dist-info/RECORD
