Metadata-Version: 2.1
Name: django-datatable-serverside-mixin
Version: 2.1.1
Summary: Server-side DataTables processing view mixin for Django
Home-page: https://github.com/matthttam/django_datatable_serverside_mixin
Author: Matt Henry
Author-email: matthttam@gmail.com
License: MIT
Classifier: Programming Language :: Python :: 3
Classifier: License :: OSI Approved :: MIT License
Classifier: Operating System :: OS Independent
Requires-Python: >=3.10
License-File: LICENSE
Requires-Dist: Django (>=3.0)
Requires-Dist: querystring-parser (>=1.2.4)
